mini_imggen_numpy_lib/__init__.py
mini_imggen_numpy_lib/mini_imggen_numpy_lib.py
mini_imggen_numpy_lib-0.2.2.dist-info/METADATA
mini_imggen_numpy_lib-0.2.2.dist-info/WHEEL
mini_imggen_numpy_lib-0.2.2.dist-info/top_level.txt
mini_imggen_numpy_lib-0.2.2.dist-info/RECORD
