Metadata-Version: 2.4
Name: mini_imggen_numpy_lib
Version: 0.2.2
Summary: A lightweight educational Python library for toy image & text generation using NumPy only.
Home-page: https://github.com/Leo62-glitch/mini_imggen_numpy_lib
Author: Léo
Classifier: Programming Language :: Python :: 3
Classifier: License :: OSI Approved :: MIT License
Classifier: Operating System :: OS Independent
Requires-Python: >=3.8
Requires-Dist: numpy
Requires-Dist: pillow
Dynamic: author
Dynamic: classifier
Dynamic: home-page
Dynamic: requires-dist
Dynamic: requires-python
Dynamic: summary
